operaton/tasks/__init__.py
operaton/tasks/api.py
operaton/tasks/config.py
operaton/tasks/deco.py
operaton/tasks/healthz.py
operaton/tasks/main.py
operaton/tasks/py.typed
operaton/tasks/types.py
operaton/tasks/utils.py
operaton/tasks/worker.py
operaton_tasks-1.0.0a6.dist-info/METADATA
operaton_tasks-1.0.0a6.dist-info/WHEEL
operaton_tasks-1.0.0a6.dist-info/entry_points.txt
operaton_tasks-1.0.0a6.dist-info/licenses/LICENSE
operaton_tasks-1.0.0a6.dist-info/RECORD
